ztfy.myams-0.1.33-py2.7-nspkg.pth
ztfy/myams/__init__.py
ztfy/myams/configuration.py
ztfy/myams/configure.zcml
ztfy/myams/form.py
ztfy/myams/layer.py
ztfy/myams/login.py
ztfy/myams/page.py
ztfy/myams/table.py
ztfy/myams/terms.py
ztfy/myams/widget.py
ztfy/myams/browser/__init__.py
ztfy/myams/browser/configuration.py
ztfy/myams/browser/configure.zcml
ztfy/myams/doctests/README.txt
ztfy/myams/interfaces/__init__.py
ztfy/myams/interfaces/configuration.py
ztfy/myams/interfaces/search.py
ztfy/myams/interfaces/widget.py
ztfy/myams/json/__init__.py
ztfy/myams/json/configure.zcml
ztfy/myams/locales/ztfy.myams.pot
ztfy/myams/locales/fr/LC_MESSAGES/ztfy.myams.mo
ztfy/myams/locales/fr/LC_MESSAGES/ztfy.myams.po
ztfy/myams/locales/fr/LC_MESSAGES/ztfy.myams.po~
ztfy/myams/resources/css/myams.css
ztfy/myams/resources/css/myams.min.css
ztfy/myams/resources/css/ext/bootstrap-3.3.2.css
ztfy/myams/resources/css/ext/bootstrap-3.3.2.min.css
ztfy/myams/resources/css/ext/bootstrap-3.3.2.min.min.css
ztfy/myams/resources/css/ext/bootstrap-modal.css
ztfy/myams/resources/css/ext/bootstrap-modal.min.css
ztfy/myams/resources/css/ext/bootstrap-modal.min.min.css
ztfy/myams/resources/css/ext/bootstrap.css.map
ztfy/myams/resources/css/ext/font-awesome-4.5.0.css
ztfy/myams/resources/css/ext/font-awesome-4.5.0.min.css
ztfy/myams/resources/css/ext/font-awesome-4.5.0.min.min.css
ztfy/myams/resources/css/ext/jquery-datetimepicker.css
ztfy/myams/resources/css/ext/jquery-datetimepicker.min.css
ztfy/myams/resources/css/ext/jquery-datetimepicker.min.min.css
ztfy/myams/resources/css/ext/jquery-fancybox-2.1.5.css
ztfy/myams/resources/css/ext/jquery-fancybox-2.1.5.min.css
ztfy/myams/resources/css/ext/jquery-fancybox-2.1.5.min.min.css
ztfy/myams/resources/css/ext/jquery-imgareaselect.css
ztfy/myams/resources/css/ext/jquery-imgareaselect.min.css
ztfy/myams/resources/css/ext/jquery-imgareaselect.min.min.css
ztfy/myams/resources/css/ext/jquery-mCustomScrollbar.css
ztfy.myams-0.1.33.dist-info/METADATA
ztfy.myams-0.1.33.dist-info/WHEEL
ztfy.myams-0.1.33.dist-info/entry_points.txt
ztfy.myams-0.1.33.dist-info/namespace_packages.txt
ztfy.myams-0.1.33.dist-info/top_level.txt
ztfy.myams-0.1.33.dist-info/RECORD
