Metadata-Version: 2.1
Name: ztfy.myams
Version: 0.1.33
Summary: ZTFY new admin/application skin
Home-page: http://hg.ztfy.org/ztfy.myams
Author: Thierry Florac
Author-email: tflorac@ulthar.net
License: zpl
Platform: UNKNOWN
Classifier: Programming Language :: Python
Requires-Dist: setuptools
Requires-Dist: fanstatic
Requires-Dist: z3c.form
Requires-Dist: z3c.formjs
Requires-Dist: z3c.formui
Requires-Dist: z3c.json
Requires-Dist: z3c.jsonrpc
Requires-Dist: z3c.language.negotiator
Requires-Dist: z3c.language.session
Requires-Dist: z3c.table
Requires-Dist: z3c.template
Requires-Dist: zope.annotation
Requires-Dist: zope.authentication
Requires-Dist: zope.component
Requires-Dist: zope.container
Requires-Dist: zope.event
Requires-Dist: zope.exceptions
Requires-Dist: zope.i18n
Requires-Dist: zope.i18nmessageid
Requires-Dist: zope.interface
Requires-Dist: zope.lifecycleevent
Requires-Dist: zope.location
Requires-Dist: zope.pagetemplate
Requires-Dist: zope.publisher
Requires-Dist: zope.schema
Requires-Dist: zope.security
Requires-Dist: zope.session
Requires-Dist: zope.site
Requires-Dist: zope.tales
Requires-Dist: zope.traversing
Requires-Dist: zope.viewlet
Requires-Dist: ztfy.baseskin
Requires-Dist: ztfy.extfile
Requires-Dist: ztfy.file
Requires-Dist: ztfy.mail
Requires-Dist: ztfy.skin
Requires-Dist: ztfy.utils
Provides-Extra: test
Requires-Dist: zope.testing ; extra == 'test'
